[
  {
    "a": "YoG",
    "d": "1720x3728",
    "n": "1",
    "t": "/thumbs/ma_01.jpg",
    "u": "ma_01.jpg"
  },
  {
    "a": "YoG",
    "d": "1720x3728",
    "n": "2",
    "t": "/thumbs/ma_02.jpg",
    "u": "ma_02.jpg"
  },
  {
    "a": "YoG",
    "d": "1720x3728",
    "n": "3",
    "t": "/thumbs/ma_03.jpg",
    "u": "ma_03.jpg"
  },
  {
    "a": "YoG",
    "d": "1720x3728",
    "n": "4",
    "t": "/thumbs/ma_04.jpg",
    "u": "ma_04.jpg"
  },
  {
    "a": "YoG",
    "d": "1720x3728",
    "n": "5",
    "t": "/thumbs/ma_05.jpg",
    "u": "ma_05.jpg"
  },
  {
    "a": "YoG",
    "d": "1720x3728",
    "n": "6",
    "t": "/thumbs/ma_06.jpg",
    "u": "ma_06.jpg"
  },{
    "a": "YoG",
    "d": "1472x3200",
    "n": "67",
    "t": "/thumbs/ma_067.jpg",
    "u": "ma_067.jpg"
  },
  {
    "a": "YoG",
    "d": "1472x3200",
    "n": "68",
    "t": "/thumbs/ma_068.jpg",
    "u": "ma_068.jpg"
  },
  {
    "a": "YoG",
    "d": "1720x3728",
    "n": "7",
    "t": "/thumbs/ma_07.jpg",
    "u": "ma_07.jpg"
  },
  {
    "a": "YoG",
    "d": "1720x3728",
    "n": "8",
    "t": "/thumbs/ma_08.jpg",
    "u": "ma_08.jpg"
  },
  {
    "a": "YoG",
    "d": "1720x3728",
    "n": "9",
    "t": "/thumbs/ma_09.jpg",
    "u": "ma_09.jpg"
  },
  {
    "a": "YoG",
    "d": "1720x3728",
    "n": "10",
    "t": "/thumbs/ma_010.jpg",
    "u": "ma_010.jpg"
  },
  {
    "a": "YoG",
    "d": "1720x3728",
    "n": "11",
    "t": "/thumbs/ma_011.jpg",
    "u": "ma_011.jpg"
  },
  {
    "a": "YoG",
    "d": "1720x3728",
    "n": "12",
    "t": "/thumbs/ma_012.jpg",
    "u": "ma_012.jpg"
  },
  {
    "a": "YoG",
    "d": "1720x3728",
    "n": "13",
    "t": "/thumbs/ma_013.jpg",
    "u": "ma_013.jpg"
  },
  {
    "a": "YoG",
    "d": "1720x3728",
    "n": "14",
    "t": "/thumbs/ma_014.jpg",
    "u": "ma_014.jpg"
  },
  {
    "a": "YoG",
    "d": "1720x3728",
    "n": "15",
    "t": "/thumbs/ma_015.jpg",
    "u": "ma_015.jpg"
  },
  {
    "a": "YoG",
    "d": "1720x3728",
    "n": "16",
    "t": "/thumbs/ma_016.jpg",
    "u": "ma_016.jpg"
  },
  {
    "a": "YoG",
    "d": "1720x3728",
    "n": "17",
    "t": "/thumbs/ma_017.jpg",
    "u": "ma_017.jpg"
  },
  {
    "a": "YoG",
    "d": "1720x3728",
    "n": "18",
    "t": "/thumbs/ma_018.jpg",
    "u": "ma_018.jpg"
  },
  {
    "a": "YoG",
    "d": "1720x3728",
    "n": "19",
    "t": "/thumbs/ma_019.jpg",
    "u": "ma_019.jpg"
  },
  {
    "a": "YoG",
    "d": "1720x3728",
    "n": "20",
    "t": "/thumbs/ma_020.jpg",
    "u": "ma_020.jpg"
  },
  {
    "a": "YoG",
    "d": "1720x3728",
    "n": "21",
    "t": "/thumbs/ma_021.jpg",
    "u": "ma_021.jpg"
  },
  {
    "a": "YoG",
    "d": "1720x3728",
    "n": "22",
    "t": "/thumbs/ma_022.jpg",
    "u": "ma_022.jpg"
  },
  {
    "a": "YoG",
    "d": "1720x3728",
    "n": "23",
    "t": "/thumbs/ma_023.jpg",
    "u": "ma_023.jpg"
  },
  {
    "a": "YoG",
    "d": "1720x3728",
    "n": "24",
    "t": "/thumbs/ma_024.jpg",
    "u": "ma_024.jpg"
  },
  {
    "a": "YoG",
    "d": "1720x3728",
    "n": "25",
    "t": "/thumbs/ma_025.jpg",
    "u": "ma_025.jpg"
  },
  {
    "a": "YoG",
    "d": "1720x3728",
    "n": "26",
    "t": "/thumbs/ma_026.jpg",
    "u": "ma_026.jpg"
  },
  {
    "a": "YoG",
    "d": "1720x3728",
    "n": "27",
    "t": "/thumbs/ma_027.jpg",
    "u": "ma_027.jpg"
  },
  {
    "a": "YoG",
    "d": "1720x3728",
    "n": "28",
    "t": "/thumbs/ma_028.jpg",
    "u": "ma_028.jpg"
  },
  {
    "a": "YoG",
    "d": "1720x3728",
    "n": "29",
    "t": "/thumbs/ma_029.jpg",
    "u": "ma_029.jpg"
  },
  {
    "a": "YoG",
    "d": "1720x3728",
    "n": "30",
    "t": "/thumbs/ma_030.jpg",
    "u": "ma_030.jpg"
  },
  {
    "a": "YoG",
    "d": "1720x3728",
    "n": "31",
    "t": "/thumbs/ma_031.jpg",
    "u": "ma_031.jpg"
  },
  {
    "a": "YoG",
    "d": "1720x3728",
    "n": "32",
    "t": "/thumbs/ma_032.jpg",
    "u": "ma_032.jpg"
  },
  {
    "a": "YoG",
    "d": "1720x3728",
    "n": "33",
    "t": "/thumbs/ma_033.jpg",
    "u": "ma_033.jpg"
  },
  {
    "a": "YoG",
    "d": "1720x3728",
    "n": "34",
    "t": "/thumbs/ma_034.jpg",
    "u": "ma_034.jpg"
  },
  {
    "a": "YoG",
    "d": "1720x3728",
    "n": "35",
    "t": "/thumbs/ma_035.jpg",
    "u": "ma_035.jpg"
  },
  {
    "a": "YoG",
    "d": "1720x3728",
    "n": "36",
    "t": "/thumbs/ma_036.jpg",
    "u": "ma_036.jpg"
  },
  {
    "a": "YoG",
    "d": "1720x3728",
    "n": "37",
    "t": "/thumbs/ma_037.jpg",
    "u": "ma_037.jpg"
  },
  {
    "a": "YoG",
    "d": "1720x3728",
    "n": "38",
    "t": "/thumbs/ma_038.jpg",
    "u": "ma_038.jpg"
  },
  {
    "a": "YoG",
    "d": "1720x3728",
    "n": "39",
    "t": "/thumbs/ma_039.jpg",
    "u": "ma_039.jpg"
  },
  {
    "a": "YoG",
    "d": "1720x3728",
    "n": "40",
    "t": "/thumbs/ma_040.jpg",
    "u": "ma_040.jpg"
  },
  {
    "a": "YoG",
    "d": "1720x3728",
    "n": "41",
    "t": "/thumbs/ma_041.jpg",
    "u": "ma_041.jpg"
  },
  {
    "a": "YoG",
    "d": "1720x3728",
    "n": "42",
    "t": "/thumbs/ma_042.jpg",
    "u": "ma_042.jpg"
  },
  {
    "a": "YoG",
    "d": "1720x3728",
    "n": "43",
    "t": "/thumbs/ma_043.jpg",
    "u": "ma_043.jpg"
  },
  {
    "a": "YoG",
    "d": "1720x3728",
    "n": "44",
    "t": "/thumbs/ma_044.jpg",
    "u": "ma_044.jpg"
  },
  {
    "a": "YoG",
    "d": "1720x3728",
    "n": "45",
    "t": "/thumbs/ma_045.jpg",
    "u": "ma_045.jpg"
  },
  {
    "a": "YoG",
    "d": "1720x3728",
    "n": "46",
    "t": "/thumbs/ma_046.jpg",
    "u": "ma_046.jpg"
  },
  {
    "a": "YoG",
    "d": "1720x3728",
    "n": "47",
    "t": "/thumbs/ma_047.jpg",
    "u": "ma_047.jpg"
  },
  {
    "a": "YoG",
    "d": "1720x3728",
    "n": "48",
    "t": "/thumbs/ma_048.jpg",
    "u": "ma_048.jpg"
  },
  {
    "a": "YoG",
    "d": "1720x3728",
    "n": "49",
    "t": "/thumbs/ma_049.jpg",
    "u": "ma_049.jpg"
  },
  {
    "a": "YoG",
    "d": "1720x3728",
    "n": "50",
    "t": "/thumbs/ma_050.jpg",
    "u": "ma_050.jpg"
  },
  {
    "a": "YoG",
    "d": "1720x3728",
    "n": "51",
    "t": "/thumbs/ma_051.jpg",
    "u": "ma_051.jpg"
  },
  {
    "a": "YoG",
    "d": "1720x3728",
    "n": "52",
    "t": "/thumbs/ma_052.jpg",
    "u": "ma_052.jpg"
  },
  {
    "a": "YoG",
    "d": "1720x3728",
    "n": "53",
    "t": "/thumbs/ma_053.jpg",
    "u": "ma_053.jpg"
  },
  {
    "a": "YoG",
    "d": "1720x3728",
    "n": "54",
    "t": "/thumbs/ma_054.jpg",
    "u": "ma_054.jpg"
  },
  {
    "a": "YoG",
    "d": "1720x3728",
    "n": "55",
    "t": "/thumbs/ma_055.jpg",
    "u": "ma_055.jpg"
  },
  {
    "a": "YoG",
    "d": "1720x3728",
    "n": "56",
    "t": "/thumbs/ma_056.jpg",
    "u": "ma_056.jpg"
  },
  {
    "a": "YoG",
    "d": "1720x3728",
    "n": "57",
    "t": "/thumbs/ma_057.jpg",
    "u": "ma_057.jpg"
  },
  {
    "a": "YoG",
    "d": "1720x3728",
    "n": "58",
    "t": "/thumbs/ma_058.jpg",
    "u": "ma_058.jpg"
  },
  {
    "a": "YoG",
    "d": "1720x3728",
    "n": "59",
    "t": "/thumbs/ma_059.jpg",
    "u": "ma_059.jpg"
  },
  {
    "a": "YoG",
    "d": "1720x3728",
    "n": "60",
    "t": "/thumbs/ma_060.jpg",
    "u": "ma_060.jpg"
  },
  {
    "a": "YoG",
    "d": "1720x3728",
    "n": "61",
    "t": "/thumbs/ma_061.jpg",
    "u": "ma_061.jpg"
  },
  {
    "a": "YoG",
    "d": "1720x3728",
    "n": "62",
    "t": "/thumbs/ma_062.jpg",
    "u": "ma_062.jpg"
  },
  {
    "a": "YoG",
    "d": "1720x3728",
    "n": "63",
    "t": "/thumbs/ma_063.jpg",
    "u": "ma_063.jpg"
  },
  {
    "a": "YoG",
    "d": "1720x3728",
    "n": "64",
    "t": "/thumbs/ma_064.jpg",
    "u": "ma_064.jpg"
  },
  {
    "a": "YoG",
    "d": "1720x3728",
    "n": "65",
    "t": "/thumbs/ma_065.jpg",
    "u": "ma_065.jpg"
  },{
    "a": "YoG",
    "d": "1720x3728",
    "n": "66",
    "t": "/thumbs/ma_066.jpg",
    "u": "ma_066.jpg"
  },
  {
    "a": "YoG",
    "d": "1472x3200",
    "n": "69",
    "t": "/thumbs/ma_069.jpg",
    "u": "ma_069.jpg"
  },
  {
    "a": "YoG",
    "d": "1472x3200",
    "n": "70",
    "t": "/thumbs/ma_070.jpg",
    "u": "ma_070.jpg"
  },
  {
    "a": "YoG",
    "d": "1472x3200",
    "n": "71",
    "t": "/thumbs/ma_071.jpg",
    "u": "ma_071.jpg"
  },
  {
    "a": "YoG",
    "d": "1472x3200",
    "n": "72",
    "t": "/thumbs/ma_072.jpg",
    "u": "ma_072.jpg"
  },
  {
    "a": "YoG",
    "d": "1472x3200",
    "n": "73",
    "t": "/thumbs/ma_073.jpg",
    "u": "ma_073.jpg"
  },
  {
    "a": "YoG",
    "d": "1472x3200",
    "n": "74",
    "t": "/thumbs/ma_074.jpg",
    "u": "ma_074.jpg"
  },
  {
    "a": "YoG",
    "d": "1472x3200",
    "n": "75",
    "t": "/thumbs/ma_075.jpg",
    "u": "ma_075.jpg"
  },
  {
    "a": "YoG",
    "d": "1472x3200",
    "n": "76",
    "t": "/thumbs/ma_076.jpg",
    "u": "ma_076.jpg"
  },
  {
    "a": "YoG",
    "d": "1472x3200",
    "n": "77",
    "t": "/thumbs/ma_077.jpg",
    "u": "ma_077.jpg"
  },
  {
    "a": "YoG",
    "d": "1472x3200",
    "n": "78",
    "t": "/thumbs/ma_078.jpg",
    "u": "ma_078.jpg"
  },
  {
    "a": "YoG",
    "d": "1472x3200",
    "n": "79",
    "t": "/thumbs/ma_079.jpg",
    "u": "ma_079.jpg"
  },
  {
    "a": "YoG",
    "d": "1472x3200",
    "n": "80",
    "t": "/thumbs/ma_080.jpg",
    "u": "ma_080.jpg"
  },
  {
    "a": "YoG",
    "d": "1472x3200",
    "n": "81",
    "t": "/thumbs/ma_081.jpg",
    "u": "ma_081.jpg"
  }
]